fastapi_ext/__init__.py
fastapi_ext/app.py
fastapi_ext/appinfo.py
fastapi_ext/auth/__init__.py
fastapi_ext/auth/models.py
fastapi_ext/auth/password.py
fastapi_ext/auth/repositories.py
fastapi_ext/auth/routes.py
fastapi_ext/auth/schemas.py
fastapi_ext/auth/services.py
fastapi_ext/auth/settings.py
fastapi_ext/auth/templates/index.html
fastapi_ext/auth/templates/login.html
fastapi_ext/auth/token.py
fastapi_ext/cli/__init__.py
fastapi_ext/forms.py
fastapi_ext/lifespan.py
fastapi_ext/session/__init__.py
fastapi_ext/session/session.py
fastapi_ext/settings.py
fastapi_ext/sqla/__init__.py
fastapi_ext/sqla/di.py
fastapi_ext/sqla/engine.py
fastapi_ext/sqla/entity_manager.py
fastapi_ext/sqla/lifespan.py
fastapi_ext/sqla/model.py
fastapi_ext/sqla/repository.py
fastapi_ext/sqla/schema.py
fastapi_ext/sqla/settings.py
fastapi_ext/templating.py
fastapi_ext/unique_id.py
fapi_ext-0.1.1.dist-info/METADATA
fapi_ext-0.1.1.dist-info/WHEEL
fapi_ext-0.1.1.dist-info/RECORD
